rwanda_locations/__init__.py
rwanda_locations/data.py
rwanda_locations/lookup.py
rwanda_locations/data/locations.json
rwanda_locations-1.1.dist-info/LICENSE
rwanda_locations-1.1.dist-info/METADATA
rwanda_locations-1.1.dist-info/WHEEL
rwanda_locations-1.1.dist-info/top_level.txt
rwanda_locations-1.1.dist-info/RECORD
