Metadata-Version: 2.1
Name: rwanda_locations
Version: 1.1
Summary: A package for working with Rwandan location metadata, including provinces, districts, sectors, cells, and villages.
Home-page: https://github.com/gisakaze/rwanda_locations
Author: Fredson Gisa Kaze
Author-email: fredson.coder@gmail.com
Classifier: Programming Language :: Python :: 3
Classifier: License :: OSI Approved :: MIT License
Classifier: Operating System :: OS Independent
Requires-Python: >=3.6
License-File: LICENSE
